odoo9_addon_oauth_provider-9.0.1.0.0-py2.7-nspkg.pth
odoo9_addon_oauth_provider-9.0.1.0.0.dist-info/DESCRIPTION.rst
odoo9_addon_oauth_provider-9.0.1.0.0.dist-info/METADATA
odoo9_addon_oauth_provider-9.0.1.0.0.dist-info/RECORD
odoo9_addon_oauth_provider-9.0.1.0.0.dist-info/WHEEL
odoo9_addon_oauth_provider-9.0.1.0.0.dist-info/metadata.json
odoo9_addon_oauth_provider-9.0.1.0.0.dist-info/namespace_packages.txt
odoo9_addon_oauth_provider-9.0.1.0.0.dist-info/top_level.txt
odoo_addons/oauth_provider/README.rst
odoo_addons/oauth_provider/__init__.py
odoo_addons/oauth_provider/__openerp__.py
odoo_addons/oauth_provider/controllers/__init__.py
odoo_addons/oauth_provider/controllers/main.py
odoo_addons/oauth_provider/models/__init__.py
odoo_addons/oauth_provider/models/oauth_provider_authorization_code.py
odoo_addons/oauth_provider/models/oauth_provider_client.py
odoo_addons/oauth_provider/models/oauth_provider_redirect_uri.py
odoo_addons/oauth_provider/models/oauth_provider_scope.py
odoo_addons/oauth_provider/models/oauth_provider_token.py
odoo_addons/oauth_provider/models/res_users.py
odoo_addons/oauth_provider/oauth2/__init__.py
odoo_addons/oauth_provider/oauth2/validator.py
odoo_addons/oauth_provider/security/ir.model.access.csv
odoo_addons/oauth_provider/security/oauth_provider_security.xml
odoo_addons/oauth_provider/templates/authorization.xml
odoo_addons/oauth_provider/tests/__init__.py
odoo_addons/oauth_provider/tests/common_test_controller.py
odoo_addons/oauth_provider/tests/common_test_oauth_provider_controller.py
odoo_addons/oauth_provider/tests/test_oauth_provider_client.py
odoo_addons/oauth_provider/tests/test_oauth_provider_controller_legacy_application.py
odoo_addons/oauth_provider/tests/test_oauth_provider_controller_mobile_application.py
odoo_addons/oauth_provider/tests/test_oauth_provider_controller_web_application.py
odoo_addons/oauth_provider/tests/test_oauth_provider_scope.py
odoo_addons/oauth_provider/tests/test_oauth_provider_token.py
odoo_addons/oauth_provider/views/oauth_provider_client.xml
odoo_addons/oauth_provider/views/oauth_provider_scope.xml
